nbkanjit/__init__.py
nbkanjit/exceptions.py
nbkanjit/manager.py
nbkanjit/signature.py
nbkanjit/testsuite/__init__.py
nbkanjit/testsuite/test_manager.py
nbkanjit/testsuite/test_signature.py
numbakit_anjit-0.2.dist-info/AUTHORS
numbakit_anjit-0.2.dist-info/LICENSE
numbakit_anjit-0.2.dist-info/METADATA
numbakit_anjit-0.2.dist-info/WHEEL
numbakit_anjit-0.2.dist-info/top_level.txt
numbakit_anjit-0.2.dist-info/zip-safe
numbakit_anjit-0.2.dist-info/RECORD
