Metadata-Version: 2.1
Name: numbakit-anjit
Version: 0.2
Summary: Annotation aware numba njit.
Home-page: https://github.com/hgrecco/numbakit-anjit
Author: Hernan E. Grecco
Author-email: hernan.grecco@gmail.com
License: BSD
Keywords: numba,jit,decorator,annotation
Platform: UNKNOWN
Classifier: Development Status :: 4 - Beta
Classifier: Intended Audience :: Developers
Classifier: Intended Audience :: Science/Research
Classifier: License :: OSI Approved :: BSD License
Classifier: Operating System :: MacOS :: MacOS X
Classifier: Operating System :: Microsoft :: Windows
Classifier: Operating System :: POSIX
Classifier: Programming Language :: Python
Classifier: Topic :: Scientific/Engineering
Classifier: Topic :: Software Development :: Libraries
Classifier: Programming Language :: Python :: 3.7
Classifier: Programming Language :: Python :: 3.8
Classifier: Programming Language :: Python :: 3.9
Requires-Python: >=3.7
Requires-Dist: packaging
Requires-Dist: numba (>=0.49)
Requires-Dist: importlib-metadata ; python_version < "3.8"
Provides-Extra: test
Requires-Dist: pytest ; extra == 'test'
Requires-Dist: pytest-mpl ; extra == 'test'
Requires-Dist: pytest-cov ; extra == 'test'
Requires-Dist: pytest-subtests ; extra == 'test'
Requires-Dist: asv ; extra == 'test'
